{
    "permission_chat.remove": "{\"enabled\":true,\"teams\":[\"Owner\",\"Developer\"],\"players\":[],\"jobs\":[],\"meta\":{}}",
    "player_RJWaters": "{\"lastPayed\":1552346168897,\"pay\":500,\"payTime\":1200000,\"maxJobs\":2,\"maxHomes\":1,\"homes\":{},\"jobs\":{},\"chatcolor\":\"white\",\"firstLogin\":1552346168782,\"lastLogin\":0,\"UUID\":null}",
    "player_xXMr_mgeeXx": "{\"lastPayed\":1551487739664,\"pay\":500,\"payTime\":1200000,\"maxJobs\":2,\"maxHomes\":1,\"homes\":{},\"jobs\":{},\"chatcolor\":\"white\",\"firstLogin\":1551487739565,\"lastLogin\":0}",
    "permission_version": "{\"enabled\":true,\"teams\":[\"Owner\",\"Developer\"],\"players\":[],\"jobs\":[],\"meta\":{}}",
    "permission_renameItem": "{\"enabled\":true,\"teams\":[\"Owner\",\"Developer\"],\"players\":[],\"meta\":{}}",
    "permission_player.setPay": "{\"enabled\":true,\"teams\":[\"Owner\",\"Developer\"],\"players\":[],\"meta\":{}}",
    "permission_perms.remove": "{\"enabled\":true,\"teams\":[\"Owner\",\"Developer\"],\"players\":[],\"meta\":{}}",
    "permission_heal": "{\"enabled\":true,\"teams\":[\"Owner\",\"Developer\"],\"players\":[],\"jobs\":[],\"meta\":{}}",
    "chatchannel_staff_only": "{\"displayName\":\"Staff-Only\",\"players\":[],\"color\":\"light_purple\",\"desc\":\"Staff Chat\"}",
    "job_miner": "{\"displayName\":\"miner\",\"pay\":0,\"payTime\":1200000,\"isOpen\":false,\"capacity\":-1,\"fireTime\":604800000}",
    "job_designer": "{\"displayName\":\"designer\",\"pay\":500,\"payTime\":1200000,\"isOpen\":false,\"capacity\":2,\"fireTime\":604800000}",
    "permission_debug": "{\"enabled\":true,\"teams\":[\"Owner\",\"Developer\"],\"players\":[],\"jobs\":[],\"meta\":{}}",
    "player_TheOddlySeagull": "{\"lastPayed\":1552742291828,\"pay\":500,\"payTime\":1200000,\"maxJobs\":2,\"maxHomes\":-1,\"homes\":{},\"jobs\":{\"farmer\":{\"lastPayed\":1552742291828}},\"talkchat\":null,\"chatcolor\":\"white\",\"firstLogin\":1551189992695,\"lastLogin\":1552731490269,\"color\":null,\"UUID\":null}",
    "permission_home": "{\"enabled\":true,\"teams\":[\"Owner\",\"Developer\",\"Beta-Tester\",\"Moderator\",\"Admin\"],\"players\":[],\"jobs\":[],\"meta\":{}}",
    "permission_tellraw": "{\"enabled\":true,\"teams\":[\"Owner\",\"Developer\"],\"players\":[],\"meta\":{}}",
    "permission_renameLore": "{\"enabled\":true,\"teams\":[\"Owner\",\"Developer\"],\"players\":[],\"meta\":{}}",
    "player_AndreiMihaiXD": "{\"lastPayed\":1552160200385,\"pay\":500,\"payTime\":1200000,\"maxJobs\":2,\"maxHomes\":1,\"homes\":{},\"jobs\":{},\"chatcolor\":\"white\",\"firstLogin\":1552158999918,\"lastLogin\":0,\"UUID\":null}",
    "permission_jobs.setPayTime": "{\"enabled\":true,\"teams\":[\"Owner\",\"Developer\"],\"players\":[],\"meta\":{}}",
    "job_mfm": "{\"displayName\":\"mfm\",\"pay\":0,\"payTime\":1200000,\"isOpen\":false,\"capacity\":10,\"fireTime\":604800000}",
    "permission_listBiomes": "{\"enabled\":true,\"teams\":[\"Owner\",\"Developer\"],\"players\":[],\"jobs\":[],\"meta\":{}}",
    "permission_chatchannel.flood_nl": "{\"enabled\":false,\"teams\":[\"Owner\",\"Developer\"],\"players\":[],\"jobs\":[],\"meta\":{}}",
    "permission_listEnchants": "{\"enabled\":true,\"teams\":[\"Owner\",\"Developer\"],\"players\":[],\"meta\":{}}",
    "permission_jobs.addPlayers": "{\"enabled\":true,\"teams\":[\"Owner\",\"Developer\"],\"players\":[],\"meta\":{}}",
    "permission_chat.color.strike": "{\"enabled\":true,\"teams\":[\"Owner\",\"Developer\"],\"players\":[],\"meta\":{}}",
    "permission_chat.color.blue": "{\"enabled\":true,\"teams\":[\"Owner\",\"Developer\"],\"players\":[],\"meta\":{}}",
    "permission_player.info": "{\"enabled\":true,\"teams\":[\"Owner\",\"Developer\"],\"players\":[],\"jobs\":[],\"meta\":{}}",
    "permission_sayas": "{\"enabled\":true,\"teams\":[\"Owner\",\"Developer\"],\"players\":[\"Filippowolf06\",\"TheCactus27\"],\"meta\":{}}",
    "permission_chat.color.dark_gray": "{\"enabled\":true,\"teams\":[\"Owner\",\"Developer\"],\"players\":[],\"meta\":{}}",
    "permission_perms.addPlayers": "{\"enabled\":true,\"teams\":[\"Owner\",\"Developer\"],\"players\":[],\"meta\":{}}",
    "permission_setHome": "{\"enabled\":true,\"teams\":[\"Owner\",\"Developer\",\"Moderator\",\"Admin\"],\"players\":[],\"jobs\":[],\"meta\":{}}",
    "job_recycle_m": "{\"displayName\":\"recycle_m\",\"pay\":0,\"payTime\":1200000,\"isOpen\":false,\"capacity\":1,\"fireTime\":604800000}",
    "permission_myIncome": "{\"enabled\":false,\"teams\":[\"Owner\",\"Developer\"],\"players\":[],\"meta\":{}}",
    "permission_jobs.playerList": "{\"enabled\":true,\"teams\":[\"Owner\",\"Developer\",\"Player\",\"player\",\"moderator\",\"Moderator\"],\"players\":[],\"meta\":{}}",
    "job_test_job": "{\"displayName\":\"Test Job\",\"pay\":500,\"payTime\":15000,\"isOpen\":false,\"capacity\":10,\"fireTime\":604800000}",
    "permission_chat.color.gray": "{\"enabled\":true,\"teams\":[\"Owner\",\"Developer\"],\"players\":[],\"meta\":{}}",
    "permission_chatchannel.tes": "{\"enabled\":false,\"teams\":[\"Owner\",\"Developer\"],\"players\":[],\"jobs\":[],\"meta\":{}}",
    "permission_chat.color.dark_blue": "{\"enabled\":true,\"teams\":[\"Owner\",\"Developer\"],\"players\":[],\"meta\":{}}",
    "permission_chat.color.gold": "{\"enabled\":true,\"teams\":[\"Owner\",\"Developer\"],\"players\":[],\"meta\":{}}",
    "permission_chat.color.underline": "{\"enabled\":true,\"teams\":[\"Owner\",\"Developer\"],\"players\":[],\"meta\":{}}",
    "permission_chat.color.light_purple": "{\"enabled\":true,\"teams\":[\"Owner\",\"Developer\"],\"players\":[],\"meta\":{}}",
    "permission_chat.setColor": "{\"enabled\":true,\"teams\":[\"Owner\",\"Developer\"],\"players\":[],\"jobs\":[],\"meta\":{}}",
    "player_SquidHCF": "{\"lastPayed\":1551300939756,\"pay\":500,\"payTime\":1200000,\"maxJobs\":2,\"maxHomes\":1,\"homes\":{},\"jobs\":{},\"chatcolor\":\"white\",\"firstLogin\":1551300939629,\"lastLogin\":0}",
    "permission_chat.color.yellow": "{\"enabled\":true,\"teams\":[\"Owner\",\"Developer\"],\"players\":[],\"jobs\":[],\"meta\":{}}",
    "player_Filippowolf06": "{\"lastPayed\":1552742463358,\"pay\":500,\"payTime\":1200000,\"maxJobs\":2,\"maxHomes\":-1,\"homes\":{},\"jobs\":{\"designer\":{\"lastPayed\":1552742463414}},\"talkchat\":\"flood_gb\",\"chatcolor\":\"white\",\"firstLogin\":1551189992803,\"lastLogin\":1552742463275,\"color\":null,\"UUID\":null}",
    "permission_perms.info": "{\"enabled\":true,\"teams\":[\"Owner\",\"Developer\"],\"players\":[],\"meta\":{}}",
    "permission_chat.color.black": "{\"enabled\":true,\"teams\":[\"Owner\",\"Developer\"],\"players\":[],\"meta\":{}}",
    "permission_jobs.setPlaces": "{\"enabled\":true,\"teams\":[\"Owner\",\"Developer\"],\"players\":[],\"meta\":{}}",
    "region_test_region": "{\"displayName\":\"test_region\",\"positions\":[],\"owner\":null,\"forSale\":false,\"salePrice\":0,\"rentTime\":-1,\"trusted\":[]}",
    "permission_chat.color.white": "{\"enabled\":true,\"teams\":[\"Owner\",\"Developer\"],\"players\":[],\"meta\":{}}",
    "player_KurisuSama": "{\"lastPayed\":1551353485688,\"pay\":500,\"payTime\":1200000,\"maxJobs\":2,\"maxHomes\":1,\"homes\":{},\"jobs\":{},\"chatcolor\":\"white\",\"firstLogin\":1551353485563,\"lastLogin\":0}",
    "permission_chat.setDisplayName": "{\"enabled\":true,\"teams\":[\"Owner\",\"Developer\"],\"players\":[],\"jobs\":[],\"meta\":{}}",
    "job_truck_driver": "{\"displayName\":\"truck_driver\",\"pay\":0,\"payTime\":1200000,\"isOpen\":false,\"capacity\":-1,\"fireTime\":604800000}",
    "region_test": "{\"displayName\":\"test\",\"positions\":[],\"owner\":null,\"height\":0,\"rentStartTime\":0,\"rentCredit\":0,\"forSale\":false,\"salePrice\":0,\"rentTime\":-1,\"trusted\":[]}",
    "permission_chat.hover": "{\"enabled\":true,\"teams\":[\"Owner\",\"Developer\"],\"players\":[],\"jobs\":[],\"meta\":{}}",
    "permission_teams.set.chatcolor": "{\"enabled\":true,\"teams\":[\"Owner\",\"Developer\"],\"players\":[],\"meta\":{}}",
    "job_car_dealer": "{\"displayName\":\"car_dealer\",\"pay\":500,\"payTime\":1200000,\"isOpen\":false,\"capacity\":4,\"fireTime\":604800000,\"companyId\":null}",
    "job_interior_architect": "{\"displayName\":\"interior_architect\",\"pay\":0,\"payTime\":1200000,\"isOpen\":false,\"capacity\":1,\"fireTime\":604800000}",
    "permission_chat.color.dark_aqua": "{\"enabled\":true,\"teams\":[\"Owner\",\"Developer\"],\"players\":[],\"meta\":{}}",
    "permission_region.clearSelection": "{\"enabled\":true,\"teams\":[\"Owner\",\"Developer\"],\"players\":[],\"jobs\":[],\"meta\":{}}",
    "permission_test": "{\"enabled\":true,\"teams\":[\"Owner\",\"Developer\"],\"players\":[],\"meta\":{}}",
    "player_Runonstof": "{\"lastPayed\":1552401010140,\"pay\":0,\"payTime\":1200000,\"maxJobs\":3,\"maxHomes\":4,\"homes\":{\"h\":{\"x\":-1914,\"y\":73,\"z\":-144},\"koek\":{\"x\":-1890,\"y\":73,\"z\":-119},\"home\":{\"x\":-1776,\"y\":76,\"z\":182}},\"jobs\":{},\"talkchat\":\"staff_only\",\"chatcolor\":\"light_purple\",\"firstLogin\":1551189992533,\"lastLogin\":1552741848834,\"color\":null,\"UUID\":null}",
    "permission_listHomes": "{\"enabled\":true,\"teams\":[\"Owner\",\"Developer\",\"Moderator\",\"Admin\"],\"players\":[],\"jobs\":[],\"meta\":{}}",
    "permission_convertNpcLoot": "{\"enabled\":true,\"teams\":[\"Owner\",\"Developer\"],\"players\":[],\"meta\":{}}",
    "permission_chat.create": "{\"enabled\":true,\"teams\":[\"Owner\",\"Developer\"],\"players\":[],\"jobs\":[],\"meta\":{}}",
    "permission_chat.color.magic": "{\"enabled\":true,\"teams\":[\"Owner\",\"Developer\"],\"players\":[],\"meta\":{}}",
    "permission_jobs.info": "{\"enabled\":true,\"teams\":[\"Owner\",\"Developer\"],\"players\":[],\"meta\":{}}",
    "permission_convert": "{\"enabled\":true,\"teams\":[\"Owner\",\"Developer\",\"Moderator\",\"Admin\",\"Staff\",\"Builder\",\"Player\"],\"players\":[],\"meta\":{}}",
    "job_taxi_driver": "{\"displayName\":\"taxi_driver\",\"pay\":0,\"payTime\":1200000,\"isOpen\":false,\"capacity\":10,\"fireTime\":604800000}",
    "permission_player.setMaxHomes": "{\"enabled\":true,\"teams\":[\"Owner\",\"Developer\"],\"players\":[],\"meta\":{}}",
    "permission_jobs.list": "{\"enabled\":false,\"teams\":[\"Owner\",\"Developer\",\"Player\",\"player\",\"moderator\",\"Moderator\"],\"players\":[],\"meta\":{}}",
    "permission_player.income": "{\"enabled\":true,\"teams\":[\"Owner\",\"Developer\"],\"players\":[],\"jobs\":[],\"meta\":{}}",
    "job_road_master": "{\"displayName\":\"road_master\",\"pay\":0,\"payTime\":1200000,\"isOpen\":false,\"capacity\":2,\"fireTime\":604800000}",
    "job_airplane_pilot": "{\"displayName\":\"airplane_pilot\",\"pay\":0,\"payTime\":1200000,\"isOpen\":false,\"capacity\":1,\"fireTime\":604800000}",
    "job_farmer": "{\"displayName\":\"farmer\",\"pay\":500,\"payTime\":1200000,\"isOpen\":false,\"capacity\":2,\"fireTime\":604800000}",
    "permission_setMagAmmo": "{\"enabled\":true,\"teams\":[\"Owner\",\"Developer\"],\"players\":[],\"jobs\":[],\"meta\":{}}",
    "player_katiepie12345": "{\"lastPayed\":1551549084762,\"pay\":500,\"payTime\":1200000,\"maxJobs\":2,\"maxHomes\":1,\"homes\":{},\"jobs\":{},\"chatcolor\":\"white\",\"firstLogin\":1551549084633,\"lastLogin\":0}",
    "permission_jobs.add": "{\"enabled\":true,\"teams\":[\"Owner\",\"Developer\"],\"players\":[],\"meta\":{}}",
    "player_Moi_Nucleosse": "{\"lastPayed\":1551904434794,\"pay\":500,\"payTime\":1200000,\"maxJobs\":2,\"maxHomes\":1,\"homes\":{},\"jobs\":{},\"chatcolor\":\"white\",\"firstLogin\":1551904434671,\"lastLogin\":0,\"UUID\":null}",
    "permission_player.setChatColor": "{\"enabled\":true,\"teams\":[\"Owner\",\"Developer\"],\"players\":[],\"jobs\":[],\"meta\":{}}",
    "permission_perms.list": "{\"enabled\":true,\"teams\":[\"Owner\",\"Developer\"],\"players\":[],\"meta\":{}}",
    "permission_chat.color.reset": "{\"enabled\":true,\"teams\":[\"Owner\",\"Developer\"],\"players\":[],\"meta\":{}}",
    "permission_chat.list": "{\"enabled\":false,\"teams\":[\"Owner\",\"Developer\"],\"players\":[],\"jobs\":[],\"meta\":{}}",
    "permission_chat.command": "{\"enabled\":true,\"teams\":[\"Owner\",\"Developer\"],\"players\":[],\"jobs\":[],\"meta\":{}}",
    "permission_chat.color.aqua": "{\"enabled\":true,\"teams\":[\"Owner\",\"Developer\"],\"players\":[],\"meta\":{}}",
    "permission_listPotions": "{\"enabled\":true,\"teams\":[\"Owner\",\"Developer\"],\"players\":[],\"jobs\":[],\"meta\":{}}",
    "permission_region.info": "{\"enabled\":true,\"teams\":[\"Owner\",\"Developer\"],\"players\":[],\"jobs\":[],\"meta\":{}}",
    "permission_listEntities": "{\"enabled\":true,\"teams\":[\"Owner\",\"Developer\"],\"players\":[],\"jobs\":[],\"meta\":{}}",
    "permission_chat.color.italic": "{\"enabled\":true,\"teams\":[\"Owner\",\"Developer\"],\"players\":[],\"meta\":{}}",
    "permission_chat.color.dark_red": "{\"enabled\":true,\"teams\":[\"Owner\",\"Developer\"],\"players\":[],\"meta\":{}}",
    "player_Roxy76me": "{\"lastPayed\":1552256336354,\"pay\":500,\"payTime\":1200000,\"maxJobs\":2,\"maxHomes\":1,\"homes\":{},\"jobs\":{},\"chatcolor\":\"white\",\"firstLogin\":1552256336232,\"lastLogin\":0,\"UUID\":null}",
    "player_JoyPaardje": "{\"lastPayed\":1551581065929,\"pay\":500,\"payTime\":1200000,\"maxJobs\":2,\"maxHomes\":1,\"homes\":{},\"jobs\":{},\"chatcolor\":\"white\",\"firstLogin\":1551443962010,\"lastLogin\":0}",
    "player_TheCactus27": "{\"lastPayed\":1552176899945,\"pay\":500,\"payTime\":1200000,\"maxJobs\":2,\"maxHomes\":1,\"homes\":{},\"jobs\":{\"car_dealer\":{\"lastPayed\":1552177159946},\"farmer\":{\"lastPayed\":1552177818268}},\"chatcolor\":\"white\",\"firstLogin\":1551311295835,\"lastLogin\":0,\"UUID\":null}",
    "permission_region.list": "{\"enabled\":true,\"teams\":[\"Owner\",\"Developer\"],\"players\":[],\"jobs\":[],\"meta\":{}}",
    "team_Moderator": "{\"chatcolor\":\"green\",\"chateffect\":null}",
    "job_hunter": "{\"displayName\":\"hunter\",\"pay\":0,\"payTime\":1200000,\"isOpen\":false,\"capacity\":-1,\"fireTime\":604800000}",
    "permission_jobs.removePlayers": "{\"enabled\":true,\"teams\":[\"Owner\",\"Developer\"],\"players\":[],\"meta\":{}}",
    "permission_perms.removeTeams": "{\"enabled\":true,\"teams\":[\"Owner\",\"Developer\"],\"players\":[],\"meta\":{}}",
    "permission_chat": "{\"enabled\":true,\"teams\":[\"Owner\",\"Developer\"],\"players\":[],\"jobs\":[],\"meta\":{}}",
    "permission_perms.addTeams": "{\"enabled\":true,\"teams\":[\"Owner\",\"Developer\"],\"players\":[],\"meta\":{}}",
    "permission_chat.color.red": "{\"enabled\":true,\"teams\":[\"Owner\",\"Developer\"],\"players\":[],\"meta\":{}}",
    "permission_perms.removePlayers": "{\"enabled\":true,\"teams\":[\"Owner\",\"Developer\"],\"players\":[],\"jobs\":[],\"meta\":{}}",
    "permission_player.setMaxJobs": "{\"enabled\":true,\"teams\":[\"Owner\",\"Developer\"],\"players\":[],\"meta\":{}}",
    "permission_player.setPayTime": "{\"enabled\":true,\"teams\":[\"Owner\",\"Developer\"],\"players\":[],\"jobs\":[],\"meta\":{}}",
    "permission_chat.color.green": "{\"enabled\":true,\"teams\":[\"Owner\",\"Developer\"],\"players\":[],\"meta\":{}}",
    "permission_chat.color.dark_purple": "{\"enabled\":true,\"teams\":[\"Owner\",\"Developer\"],\"players\":[],\"meta\":{}}",
    "permission_test.region.build": "{\"enabled\":true,\"teams\":[\"Owner\",\"Developer\"],\"players\":[],\"meta\":{}}",
    "permission_perms.setEnabled": "{\"enabled\":true,\"teams\":[\"Owner\",\"Developer\"],\"players\":[],\"meta\":{}}",
    "permission_convertTrader": "{\"enabled\":true,\"teams\":[\"Owner\",\"Developer\"],\"players\":[],\"meta\":{}}",
    "permission_chat.color.dark_green": "{\"enabled\":true,\"teams\":[\"Owner\",\"Developer\"],\"players\":[],\"meta\":{}}",
    "permission_jobs.setDisplayName": "{\"enabled\":true,\"teams\":[\"Owner\",\"Developer\"],\"players\":[],\"meta\":{}}",
    "job_lumberjack": "{\"displayName\":\"lumberjack\",\"pay\":0,\"payTime\":1200000,\"isOpen\":false,\"capacity\":-1,\"fireTime\":604800000}",
    "chatchannel_flood_gb": "{\"displayName\":\"Flood-GB\",\"players\":[],\"color\":\"blue\",\"desc\":\"English Chat\"}",
    "job_oil_t": "{\"displayName\":\"oil_t\",\"pay\":0,\"payTime\":1200000,\"isOpen\":false,\"capacity\":1,\"fireTime\":604800000}",
    "player_Tigerlordz": "{\"lastPayed\":1552619096169,\"pay\":500,\"payTime\":1200000,\"maxJobs\":2,\"maxHomes\":1,\"homes\":{},\"jobs\":{},\"talkchat\":null,\"chatcolor\":\"white\",\"firstLogin\":1552619095215,\"lastLogin\":0,\"color\":null,\"UUID\":null}",
    "permission_chat.color": "{\"enabled\":true,\"teams\":[\"Owner\",\"Developer\"],\"players\":[],\"jobs\":[],\"meta\":{}}",
    "job_oil_p": "{\"displayName\":\"oil_p\",\"pay\":0,\"payTime\":1200000,\"isOpen\":false,\"capacity\":1,\"fireTime\":604800000}",
    "permission_chatchannel.test_2": "{\"enabled\":false,\"teams\":[\"Owner\",\"Developer\"],\"players\":[],\"jobs\":[],\"meta\":{}}",
    "permission_jobs.setPay": "{\"enabled\":true,\"teams\":[\"Owner\",\"Developer\"],\"players\":[],\"meta\":{}}",
    "player_CitrineFool6429": "{\"lastPayed\":1551593056971,\"pay\":500,\"payTime\":1200000,\"maxJobs\":2,\"maxHomes\":1,\"homes\":{},\"jobs\":{},\"chatcolor\":\"white\",\"firstLogin\":1551271658609,\"lastLogin\":0}",
    "player_ninjawarior200": "{\"lastPayed\":1552586150038,\"pay\":500,\"payTime\":1200000,\"maxJobs\":2,\"maxHomes\":1,\"homes\":{},\"jobs\":{},\"chatcolor\":\"white\",\"firstLogin\":1552159545715,\"lastLogin\":0,\"color\":null,\"UUID\":null}",
    "permission_delHome": "{\"enabled\":true,\"teams\":[\"Owner\",\"Developer\",\"Moderator\",\"Admin\"],\"players\":[],\"jobs\":[],\"meta\":{}}",
    "permission_giveMoney": "{\"enabled\":true,\"teams\":[\"Owner\",\"Developer\"],\"players\":[],\"meta\":{}}",
    "permission_jobs.reload": "{\"enabled\":true,\"teams\":[\"Owner\",\"Developer\"],\"players\":[],\"meta\":{}}",
    "permission_jobs.setFireTime": "{\"enabled\":true,\"teams\":[\"Owner\",\"Developer\"],\"players\":[],\"meta\":{}}",
    "player_Skylur159": "{\"lastPayed\":1552551249400,\"pay\":500,\"payTime\":1200000,\"maxJobs\":2,\"maxHomes\":1,\"homes\":{},\"jobs\":{},\"chatcolor\":\"white\",\"firstLogin\":1552551249005,\"lastLogin\":0,\"color\":null,\"UUID\":null}",
    "permission_chat.color.bold": "{\"enabled\":true,\"teams\":[\"Owner\"],\"players\":[],\"jobs\":[],\"meta\":{}}",
    "permission_region.add": "{\"enabled\":true,\"teams\":[\"Owner\",\"Developer\"],\"players\":[],\"jobs\":[],\"meta\":{}}",
    "chatchannel_flood_nl": "{\"displayName\":\"Flood-NL\",\"players\":[\"ninjawarior200\"],\"color\":\"blue\",\"desc\":\"Nederlandse Chat\"}",
    "permission_test.region.build.all": "{\"enabled\":true,\"teams\":[\"Owner\",\"Developer\"],\"players\":[],\"meta\":{}}",
    "permission_chatchannel.flood_gb": "{\"enabled\":false,\"teams\":[\"Owner\",\"Developer\"],\"players\":[],\"jobs\":[],\"meta\":{}}",
    "permission_ctest": "{\"enabled\":true,\"teams\":[\"Owner\",\"Developer\"],\"players\":[],\"jobs\":[],\"meta\":{}}",
    "permission_chat.leave": "{\"enabled\":false,\"teams\":[\"Owner\",\"Developer\"],\"players\":[],\"jobs\":[],\"meta\":{}}",
    "permission_chat.join": "{\"enabled\":false,\"teams\":[\"Owner\",\"Developer\"],\"players\":[],\"jobs\":[],\"meta\":{}}",
    "player__shyver_": "{\"lastPayed\":1551978832498,\"pay\":500,\"payTime\":1200000,\"maxJobs\":2,\"maxHomes\":1,\"homes\":{},\"jobs\":{},\"chatcolor\":\"white\",\"firstLogin\":1551978832388,\"lastLogin\":0,\"UUID\":null}",
    "permission_test.region": "{\"enabled\":true,\"teams\":[\"Owner\",\"Developer\"],\"players\":[],\"meta\":{}}",
    "permission_test_permission": "{\"enabled\":true,\"teams\":[\"Owner\",\"Developer\"],\"players\":[],\"meta\":{}}",
    "player_bluejoe12345": "{\"lastPayed\":1551292362089,\"pay\":500,\"payTime\":1200000,\"maxJobs\":2,\"maxHomes\":1,\"homes\":{},\"jobs\":{},\"chatcolor\":\"white\",\"firstLogin\":1551285160317,\"lastLogin\":0}",
    "permission_convertMoney": "{\"enabled\":true,\"teams\":[\"Owner\",\"Developer\",\"Player\",\"Moderator\"],\"players\":[],\"meta\":{}}",
    "player_LordOfTheFurries": "{\"lastPayed\":1552198438921,\"pay\":500,\"payTime\":1200000,\"maxJobs\":2,\"maxHomes\":1,\"homes\":{},\"jobs\":{},\"chatcolor\":\"white\",\"firstLogin\":1552198438521,\"lastLogin\":0,\"UUID\":null}",
    "permission_region.select": "{\"enabled\":true,\"teams\":[\"Owner\",\"Developer\"],\"players\":[],\"jobs\":[],\"meta\":{}}",
    "permission_chatchannel.staff_only": "{\"enabled\":true,\"teams\":[\"Owner\",\"Developer\"],\"players\":[],\"jobs\":[],\"meta\":{}}",
    "player_icehawk63": "{\"lastPayed\":1551497220827,\"pay\":500,\"payTime\":1200000,\"maxJobs\":2,\"maxHomes\":1,\"homes\":{},\"jobs\":{},\"chatcolor\":\"white\",\"firstLogin\":1551497220466,\"lastLogin\":0}"
}
